bump440/__init__.py
bump440/bump.py
bump440/cli.py
bump440/exceptions.py
bump440/io.py
bump440/logger.py
bump440/parts.py
bump440/versions.py
bump440-0.1.0.dev1.dist-info/entry_points.txt
bump440-0.1.0.dev1.dist-info/LICENSE
bump440-0.1.0.dev1.dist-info/WHEEL
bump440-0.1.0.dev1.dist-info/METADATA
bump440-0.1.0.dev1.dist-info/RECORD
