Metadata-Version: 2.1
Name: bump440
Version: 0.1.0.dev1
Summary: This is the __init__.py file for the bump440 module.
Author-email: Azat <8280770+azataiot@users.noreply.github.com>
Requires-Python: >=3.11
Classifier: License :: OSI Approved :: MIT License
Classifier: Programming Language :: Python :: 3.11
Project-URL: Home, https://github.com/azataiot/bump440 
Project-URL: Source, https://github.com/azataiot/bump440 
